{
  "openapi": "3.0.1",
  "info": {
    "title": "Countries",
    "version": "1.0"
  },
  "paths": {
    "/api/Countries/block": {
      "post": {
        "tags": [
          "Countries"
        ],
        "requestBody": {
          "content": {
            "application/json": {
              "schema": {
                "$ref": "#/components/schemas/BlockCountryRequest"
              }
            },
            "text/json": {
              "schema": {
                "$ref": "#/components/schemas/BlockCountryRequest"
              }
            },
            "application/*+json": {
              "schema": {
                "$ref": "#/components/schemas/BlockCountryRequest"
              }
            }
          }
        },
        "responses": {
          "200": {
            "description": "OK"
          }
        }
      }
    },
    "/api/Countries/block/{countryCode}": {
      "delete": {
        "tags": [
          "Countries"
        ],
        "parameters": [
          {
            "name": "countryCode",
            "in": "path",
            "required": true,
            "schema": {
              "type": "string"
            }
          }
        ],
        "responses": {
          "200": {
            "description": "OK"
          }
        }
      }
    },
    "/api/Countries/blocked": {
      "get": {
        "tags": [
          "Countries"
        ],
        "parameters": [
          {
            "name": "Page",
            "in": "query",
            "schema": {
              "type": "integer",
              "format": "int32"
            }
          },
          {
            "name": "PageSize",
            "in": "query",
            "schema": {
              "type": "integer",
              "format": "int32"
            }
          },
          {
            "name": "SearchTerm",
            "in": "query",
            "schema": {
              "type": "string"
            }
          }
        ],
        "responses": {
          "200": {
            "description": "OK"
          }
        }
      }
    },
    "/api/Countries/temporal-block": {
      "post": {
        "tags": [
          "Countries"
        ],
        "requestBody": {
          "content": {
            "application/json": {
              "schema": {
                "$ref": "#/components/schemas/BlockCountryRequest"
              }
            },
            "text/json": {
              "schema": {
                "$ref": "#/components/schemas/BlockCountryRequest"
              }
            },
            "application/*+json": {
              "schema": {
                "$ref": "#/components/schemas/BlockCountryRequest"
              }
            }
          }
        },
        "responses": {
          "200": {
            "description": "OK"
          }
        }
      }
    },
    "/api/IP/country-lookup/{ipAddress}": {
      "get": {
        "tags": [
          "IP"
        ],
        "parameters": [
          {
            "name": "ipAddress",
            "in": "path",
            "required": true,
            "schema": {
              "type": "string"
            }
          }
        ],
        "responses": {
          "200": {
            "description": "OK"
          }
        }
      }
    },
    "/api/IP/check-block/{ipAddress}": {
      "get": {
        "tags": [
          "IP"
        ],
        "parameters": [
          {
            "name": "ipAddress",
            "in": "path",
            "required": true,
            "schema": {
              "type": "string"
            }
          }
        ],
        "responses": {
          "200": {
            "description": "OK"
          }
        }
      }
    },
    "/api/Logs/blocked-attempts": {
      "get": {
        "tags": [
          "Logs"
        ],
        "parameters": [
          {
            "name": "Page",
            "in": "query",
            "schema": {
              "type": "integer",
              "format": "int32"
            }
          },
          {
            "name": "PageSize",
            "in": "query",
            "schema": {
              "type": "integer",
              "format": "int32"
            }
          },
          {
            "name": "SearchTerm",
            "in": "query",
            "schema": {
              "type": "string"
            }
          }
        ],
        "responses": {
          "200": {
            "description": "OK"
          }
        }
      }
    }
  },
  "components": {
    "schemas": {
      "BlockCountryRequest": {
        "type": "object",
        "properties": {
          "countryCode": {
            "type": "string",
            "nullable": true
          },
          "isTemporary": {
            "type": "boolean"
          },
          "durationMinutes": {
            "type": "integer",
            "format": "int32",
            "nullable": true
          }
        },
        "additionalProperties": false
      }
    }
  }
}